nonebot_plugin_wsshd/__init__.py
nonebot_plugin_wsshd/config.py
nonebot_plugin_wsshd/core/server/__init__.py
nonebot_plugin_wsshd/core/server/callbacks.py
nonebot_plugin_wsshd/core/server/client.py
nonebot_plugin_wsshd/core/server/client_types.py
nonebot_plugin_wsshd/core/server/server_types.py
nonebot_plugin_wsshd/core/server/shared.py
nonebot_plugin_wsshd/core/server/store.py
nonebot_plugin_wsshd/core/server/ws.py
nonebot_plugin_wsshd/events/bot.py
nonebot_plugin_wsshd-0.0.2.dist-info/METADATA
nonebot_plugin_wsshd-0.0.2.dist-info/WHEEL
nonebot_plugin_wsshd-0.0.2.dist-info/RECORD
